{
  "tiles": {
    "0": {
      "color": "white"
    },
    "1": {
      "color": "black"
    },
    "2": {
      "image": "tiles/grass.png"
    },
    "3": {
      "image": "tiles/water.png"
    },
    "4": {
      "color": "gray"
    },
    "5": {
      "image": "tiles/brick.png"
    },
    "6": {
      "image": "tiles/flowers.png"
    },
    "7": {
      "image": "tiles/stone.png"
    }
  },
  "entities": {
    "bot": {
      "image": "entities/roomba1.png",
      "type": "coderunner",
      "x": -1,
      "y": 0
    },
    "flag": {
      "image": "tiles/flag.png",
      "type": "",
      "x": 2,
      "y": 7
    },
    "fire": {
      "image": "tiles/fire.png",
      "type": "",
      "x": 2,
      "y": 7
    }
  },
  "terrain": [
    [
      2,
      3,
      3,
      4,
      3,
      3,
      3,
      3,
      3,
      3
    ],
    [
      2,
      2,
      3,
      3,
      3,
      3,
      4,
      4,
      3,
      3
    ],
    [
      2,
      2,
      2,
      2,
      3,
      3,
      4,
      3,
      3,
      3
    ],
    [
      2,
      2,
      2,
      2,
      2,
      3,
      3,
      3,
      3,
      3
    ],
    [
      2,
      2,
      2,
      2,
      2,
      2,
      3,
      3,
      3,
      3
    ],
    [
      2,
      2,
      2,
      2,
      2,
      2,
      2,
      3,
      3,
      3
    ],
    [
      2,
      2,
      7,
      2,
      2,
      2,
      2,
      2,
      2,
      2
    ],
    [
      2,
      7,
      2,
      7,
      2,
      2,
      2,
      2,
      2,
      2
    ],
    [
      2,
      2,
      7,
      2,
      2,
      2,
      2,
      2,
      2,
      2
    ],
    [
      2,
      2,
      2,
      2,
      2,
      2,
      2,
      2,
      2,
      2
    ]
  ]
}
